convert_color_codes.py
convert_color_codes-1.0.3.dist-info/METADATA
convert_color_codes-1.0.3.dist-info/WHEEL
convert_color_codes-1.0.3.dist-info/top_level.txt
convert_color_codes-1.0.3.dist-info/RECORD
