Metadata-Version: 2.1
Name: convert-color-codes
Version: 1.0.3
Summary: Conversion between variations of color codes. HSV/HSB or RGB or CMYK or HSL
Author-email: PRMPSmart <prmpsmart@gmail.com>
Project-URL: Homepage, https://github.com/prmpsmart/convert_color_codes
Keywords: color,color_codes,convert_color
Classifier: Programming Language :: Python
Classifier: Programming Language :: Python :: 3
